cli_git/__init__.py
cli_git/__main__.py
cli_git/cli.py
cli_git/commands/__init__.py
cli_git/commands/completion.py
cli_git/commands/info.py
cli_git/commands/init.py
cli_git/commands/private_mirror.py
cli_git/commands/update_mirrors.py
cli_git/commands/modules/__init__.py
cli_git/commands/modules/interactive.py
cli_git/commands/modules/scan.py
cli_git/commands/modules/workflow_updater.py
cli_git/completion/__init__.py
cli_git/completion/completers.py
cli_git/core/__init__.py
cli_git/core/mirrorkeep.py
cli_git/core/workflow.py
cli_git/templates/__init__.py
cli_git/templates/mirror-sync.yml.j2
cli_git/utils/__init__.py
cli_git/utils/config.py
cli_git/utils/gh.py
cli_git/utils/git.py
cli_git/utils/schedule.py
cli_git/utils/validators.py
cli_git/templates/__init__.py
cli_git/templates/mirror-sync.yml.j2
cli_git-2.2.0.dist-info/METADATA
cli_git-2.2.0.dist-info/WHEEL
cli_git-2.2.0.dist-info/entry_points.txt
cli_git-2.2.0.dist-info/licenses/LICENSE
cli_git-2.2.0.dist-info/RECORD
