Metadata-Version: 2.4
Name: cli-git
Version: 2.2.0
Summary: A modern Python CLI tool for Git operations
Author-email: Kang Hee Yong <cagojeiger@naver.com>
License-File: LICENSE
Keywords: cli,git,tool
Classifier: Development Status :: 3 - Alpha
Classifier: Environment :: Console
Classifier: Intended Audience :: Developers
Classifier: License :: OSI Approved :: MIT License
Classifier: Programming Language :: Python :: 3
Classifier: Programming Language :: Python :: 3.11
Classifier: Programming Language :: Python :: 3.12
Classifier: Topic :: Software Development :: Version Control :: Git
Classifier: Topic :: Utilities
Requires-Python: >=3.11
Requires-Dist: jinja2>=3.1.0
Requires-Dist: tomlkit>=0.13.2
Requires-Dist: typer>=0.16.0
